ifstate/__init__.py
ifstate/ifstate.py
ifstate/shell.py
ifstate/vrrp.py
ifstate-2.2.3.dist-info/licenses/LICENSE
libifstate/__init__.py
libifstate/exception.py
libifstate/log.py
libifstate/util.py
libifstate/address/__init__.py
libifstate/bpf/__init__.py
libifstate/bpf/ctypes.py
libifstate/bpf/map.py
libifstate/brport/__init__.py
libifstate/fdb/__init__.py
libifstate/hook/__init__.py
libifstate/hook/wrapper.sh
libifstate/link/__init__.py
libifstate/link/base.py
libifstate/link/dsa.py
libifstate/link/physical.py
libifstate/link/tun.py
libifstate/link/veth.py
libifstate/link/vlan.py
libifstate/neighbour/__init__.py
libifstate/netns/__init__.py
libifstate/parser/__init__.py
libifstate/parser/base.py
libifstate/parser/yaml.py
libifstate/routing/__init__.py
libifstate/schema/2/ifstate.conf.schema.json
libifstate/sysctl/__init__.py
libifstate/tc/__init__.py
libifstate/wireguard/__init__.py
libifstate/xdp/__init__.py
ifstate-2.2.3.dist-info/METADATA
ifstate-2.2.3.dist-info/WHEEL
ifstate-2.2.3.dist-info/entry_points.txt
ifstate-2.2.3.dist-info/top_level.txt
ifstate-2.2.3.dist-info/RECORD
