Metadata-Version: 2.4
Name: ifstate
Version: 2.2.3
Summary: Manage host interface settings in a declarative manner
Home-page: https://ifstate.net/
Author: Thomas Liske
Author-email: thomas@fiasko-nw.net
License: GPL3+
Requires-Python: >=3.10
License-File: LICENSE
Requires-Dist: jsonschema
Requires-Dist: pyroute2!=0.9.3
Requires-Dist: pyyaml
Requires-Dist: setproctitle
Provides-Extra: shell
Requires-Dist: pygments; extra == "shell"
Dynamic: author
Dynamic: author-email
Dynamic: description
Dynamic: description-content-type
Dynamic: home-page
Dynamic: license
Dynamic: license-file
Dynamic: provides-extra
Dynamic: requires-dist
Dynamic: requires-python
Dynamic: summary
